<Properties StartupConfiguration="{07AC083A-B1E2-437F-8ACD-0B959EB3FB4A}|Default">
  <MonoDevelop.Ide.ItemProperties.CleverTap.Bindings.Android PreferredExecutionTarget="Android.Pixel_3a_API_30_x86" />
  <MonoDevelop.Ide.Workbench ActiveDocument="obj/Release/generated/src/Com.Clevertap.Android.Sdk.IBaseCTApiListener.cs">
    <Files>
      <File FileName="obj/Release/generated/src/Com.Clevertap.Android.Sdk.IBaseCTApiListener.cs" Line="151" Column="18" />
    </Files>
    <Pads>
      <Pad Id="ProjectPad">
        <State name="__root__">
          <Node name="CleverTap.Bindings.Android" expanded="True">
            <Node name="CleverTap.Bindings.Android" expanded="True">
              <Node name="References" expanded="True" />
              <Node name="Additions" expanded="True" />
              <Node name="Jars" expanded="True" />
              <Node name="Properties" expanded="True" />
              <Node name="Transforms" expanded="True" />
            </Node>
          </Node>
        </State>
      </Pad>
    </Pads>
  </MonoDevelop.Ide.Workbench>
  <MonoDevelop.Ide.DebuggingService.PinnedWatches />
  <MonoDevelop.Ide.Workspace ActiveConfiguration="Release" />
  <MonoDevelop.Ide.DebuggingService.Breakpoints>
    <BreakpointStore />
  </MonoDevelop.Ide.DebuggingService.Breakpoints>
  <MultiItemStartupConfigurations />
</Properties>